fabric_mcp.py
microsoft_fabric_mcp-0.1.4.dist-info/licenses/LICENSE
microsoft_fabric_mcp-0.1.4.dist-info/METADATA
microsoft_fabric_mcp-0.1.4.dist-info/WHEEL
microsoft_fabric_mcp-0.1.4.dist-info/entry_points.txt
microsoft_fabric_mcp-0.1.4.dist-info/top_level.txt
microsoft_fabric_mcp-0.1.4.dist-info/RECORD
