Metadata-Version: 2.4
Name: microsoft-fabric-mcp
Version: 0.1.4
Summary: Safe, read-only MCP server for Microsoft Fabric - 25 tools for data engineers
Author-email: August Asheim Birkeland <augbir@gmail.com>
License: MIT
Project-URL: Homepage, https://github.com/Augustab/microsoft_fabric_mcp
Project-URL: Repository, https://github.com/Augustab/microsoft_fabric_mcp
Project-URL: Issues, https://github.com/Augustab/microsoft_fabric_mcp/issues
Keywords: microsoft-fabric,mcp,model-context-protocol,data-engineering,fabric-api
Classifier: Development Status :: 4 - Beta
Classifier: Intended Audience :: Developers
Classifier: License :: OSI Approved :: MIT License
Classifier: Programming Language :: Python :: 3
Classifier: Programming Language :: Python :: 3.12
Classifier: Topic :: Software Development :: Libraries :: Python Modules
Classifier: Topic :: Database
Classifier: Topic :: Scientific/Engineering
Requires-Python: >=3.12
License-File: LICENSE
Requires-Dist: azure-identity>=1.20.0
Requires-Dist: cachetools>=6.2.0
Requires-Dist: deltalake>=0.25.4
Requires-Dist: mcp[cli]>=1.3.0
Requires-Dist: requests>=2.32.3
Dynamic: license-file
